morningstar_data/__init__.py
morningstar_data/_base.py
morningstar_data/_utils.py
morningstar_data/_version.py
morningstar_data/datalake/__init__.py
morningstar_data/datalake/_data_objects/__init__.py
morningstar_data/datalake/_data_objects/_file.py
morningstar_data/datalake/_data_objects/_table.py
morningstar_data/datalake/_data_objects/csvfile.py
morningstar_data/datalake/_data_objects/temptable.py
morningstar_data/datalake/_error_messages.py
morningstar_data/datalake/_exceptions.py
morningstar_data/datalake/base.py
morningstar_data/direct/__init__.py
morningstar_data/direct/_api.py
morningstar_data/direct/_backend_apis/__init__.py
morningstar_data/direct/_backend_apis/_delivery_backend.py
morningstar_data/direct/_backend_apis/_holdings_backend.py
morningstar_data/direct/_backend_apis/_signed_url_backend.py
morningstar_data/direct/_base_api.py
morningstar_data/direct/_config.py
morningstar_data/direct/_config_key.py
morningstar_data/direct/_core_api.py
morningstar_data/direct/_data_objects/__init__.py
morningstar_data/direct/_data_objects/_custom_data_points_types.py
morningstar_data/direct/_data_objects/_data_points_object.py
morningstar_data/direct/_data_objects/_investments_object.py
morningstar_data/direct/_data_point.py
morningstar_data/direct/_data_type.py
morningstar_data/direct/_decorator.py
morningstar_data/direct/_error_messages.py
morningstar_data/direct/_exceptions.py
morningstar_data/direct/_investment/__init__.py
morningstar_data/direct/_investment/_asset_flow_data.py
morningstar_data/direct/_investment/_common.py
morningstar_data/direct/_investment/_data.py
morningstar_data/direct/_investment/_normal_data.py
morningstar_data/direct/_investment/_peer_group_data.py
morningstar_data/direct/_portfolio/__init__.py
morningstar_data/direct/_portfolio/_common.py
morningstar_data/direct/_portfolio/_portfolio_holdings_entity.py
morningstar_data/direct/_portfolio/_portfolio_settings.py
morningstar_data/direct/_portfolio/_portfolio_type.py
morningstar_data-1.12.1.dist-info/LICENSE
morningstar_data-1.12.1.dist-info/METADATA
morningstar_data-1.12.1.dist-info/WHEEL
morningstar_data-1.12.1.dist-info/RECORD
