Metadata-Version: 2.1
Name: morningstar-data
Version: 1.12.1
Summary: Morningstar Data
Home-page: https://www.morningstar.com/products/md-python-package
License: Apache-2.0
Author: Morningstar, Inc.
Requires-Python: >=3.8,<4.0
Classifier: License :: OSI Approved :: Apache Software License
Classifier: Programming Language :: Python :: 3
Classifier: Programming Language :: Python :: 3.8
Classifier: Programming Language :: Python :: 3.9
Classifier: Programming Language :: Python :: 3.10
Classifier: Programming Language :: Python :: 3.11
Requires-Dist: PyJWT (>=2.4.0,<3.0.0)
Requires-Dist: boto3 (>=1.20.1,<2.0.0)
Requires-Dist: numpy
Requires-Dist: pandas (>=1.5.3,<3)
Requires-Dist: polling2 (==0.5.0)
Requires-Dist: pyarrow (>=10.0.1)
Requires-Dist: requests (>=2.28.2,<3.0.0)
Requires-Dist: simplejson (>=3)
Requires-Dist: tenacity (>=8.2.2,<9.0.0)
Requires-Dist: typeguard (>=2.13.3,<3.0.0)
Project-URL: Documentation, https://docs-analyticslab.morningstar.com/latest/index.html
